[{"flightNumber":"1287","aircraftType":"738","origin":"MIA","destination":"ORD","departureTime":"2018-03-10T06:50-05:00","arrivalTime":"2018-03-10T09:25-06:00","flightStatus":"On-Time","cost":"384"},{"flightNumber":"334","aircraftType":"738","origin":"MIA","destination":"ORD","departureTime":"2018-03-10T08:45-05:00","arrivalTime":"2018-03-10T11:13-06:00","flightStatus":"On-Time","cost":"331"},{"flightNumber":"1567","aircraftType":"738","origin":"MIA","destination":"ORD","departureTime":"2018-03-10T10:15-05:00","arrivalTime":"2018-03-10T12:48-06:00","flightStatus":"On-Time","cost":"415"},{"flightNumber":"541","aircraftType":"321","origin":"MIA","destination":"ORD","departureTime":"2018-03-10T12:01-05:00","arrivalTime":"2018-03-10T14:30-06:00","flightStatus":"On-Time","cost":"336"},{"flightNumber":"1090","aircraftType":"32B","origin":"MIA","destination":"ORD","departureTime":"2018-03-10T13:50-05:00","arrivalTime":"2018-03-10T16:18-06:00","flightStatus":"On-Time","cost":"354"},{"flightNumber":"1284","aircraftType":"738","origin":"MIA","destination":"ORD","departureTime":"2018-03-10T16:05-05:00","arrivalTime":"2018-03-10T18:38-06:00","flightStatus":"On-Time","cost":"389"},{"flightNumber":"1109","aircraftType":"738","origin":"MIA","destination":"ORD","departureTime":"2018-03-10T16:55-05:00","arrivalTime":"2018-03-10T19:27-06:00","flightStatus":"On-Time","cost":"395"},{"flightNumber":"1448","aircraftType":"738","origin":"MIA","destination":"ORD","departureTime":"2018-03-10T18:05-05:00","arrivalTime":"2018-03-10T20:39-06:00","flightStatus":"On-Time","cost":"395"},{"flightNumber":"2394","aircraftType":"738","origin":"MIA","destination":"ORD","departureTime":"2018-03-10T18:30-05:00","arrivalTime":"2018-03-10T21:01-06:00","flightStatus":"On-Time","cost":"295"},{"flightNumber":"1612","aircraftType":"738","origin":"MIA","destination":"ORD","departureTime":"2018-03-10T19:35-05:00","arrivalTime":"2018-03-10T22:07-06:00","flightStatus":"On-Time","cost":"395"},{"flightNumber":"2521","aircraftType":"738","origin":"MIA","destination":"ORD","departureTime":"2018-03-10T21:30-05:00","arrivalTime":"2018-03-10T23:57-06:00","flightStatus":"On-Time","cost":"290"},{"flightNumber":"1202","aircraftType":"738","origin":"MIA","destination":"ORD","departureTime":"2018-03-10T11:11-05:00","arrivalTime":"2018-03-10T16:01-06:00","flightStatus":"On-Time","cost":"401"}]