[{"flightNumber":"1352","aircraftType":"32B","origin":"MIA","destination":"LAX","departureTime":"2018-03-23T06:55-04:00","arrivalTime":"2018-03-23T10:15-07:00","flightStatus":"On-Time","cost":"323"},{"flightNumber":"295","aircraftType":"32B","origin":"MIA","destination":"LAX","departureTime":"2018-03-23T08:35-04:00","arrivalTime":"2018-03-23T11:49-07:00","flightStatus":"On-Time","cost":"329"},{"flightNumber":"1627","aircraftType":"32B","origin":"MIA","destination":"LAX","departureTime":"2018-03-23T12:00-04:00","arrivalTime":"2018-03-23T15:02-07:00","flightStatus":"On-Time","cost":"331"},{"flightNumber":"2543","aircraftType":"32B","origin":"MIA","destination":"LAX","departureTime":"2018-03-23T14:10-04:00","arrivalTime":"2018-03-23T17:15-07:00","flightStatus":"On-Time","cost":"356"},{"flightNumber":"2435","aircraftType":"32B","origin":"MIA","destination":"LAX","departureTime":"2018-03-23T15:30-04:00","arrivalTime":"2018-03-23T18:35-07:00","flightStatus":"On-Time","cost":"371"},{"flightNumber":"275","aircraftType":"772","origin":"MIA","destination":"LAX","departureTime":"2018-03-23T17:30-04:00","arrivalTime":"2018-03-23T20:28-07:00","flightStatus":"On-Time","cost":"330"},{"flightNumber":"358","aircraftType":"32B","origin":"MIA","destination":"LAX","departureTime":"2018-03-23T19:50-04:00","arrivalTime":"2018-03-23T23:13-07:00","flightStatus":"On-Time","cost":"378"},{"flightNumber":"1147","aircraftType":"738","origin":"MIA","destination":"LAX","departureTime":"2018-03-23T21:35-04:00","arrivalTime":"2018-03-24T00:53-07:00","flightStatus":"On-Time","cost":"314"}]