[{"flightNumber":"50","aircraftType":"77W","origin":"DFW","destination":"LHR","departureTime":"2018-03-29T15:45-05:00","arrivalTime":"2018-03-30T06:55+01:00","flightStatus":"On-Time","cost":"424"},{"flightNumber":"6153","aircraftType":"747","origin":"DFW","destination":"LHR","departureTime":"2018-03-29T18:00-05:00","arrivalTime":"2018-03-30T09:05+01:00","flightStatus":"On-Time","cost":"374"},{"flightNumber":"78","aircraftType":"77W","origin":"DFW","destination":"LHR","departureTime":"2018-03-29T19:00-05:00","arrivalTime":"2018-03-30T10:25+01:00","flightStatus":"On-Time","cost":"300"},{"flightNumber":"80","aircraftType":"772","origin":"DFW","destination":"LHR","departureTime":"2018-03-29T21:55-05:00","arrivalTime":"2018-03-30T13:15+01:00","flightStatus":"On-Time","cost":"316"}]