[{"flightNumber":"1287","aircraftType":"738","origin":"MIA","destination":"ORD","departureTime":"2018-03-24T06:50-04:00","arrivalTime":"2018-03-24T09:25-05:00","flightStatus":"On-Time","cost":"319"},{"flightNumber":"334","aircraftType":"738","origin":"MIA","destination":"ORD","departureTime":"2018-03-24T08:45-04:00","arrivalTime":"2018-03-24T11:13-05:00","flightStatus":"On-Time","cost":"376"},{"flightNumber":"1567","aircraftType":"738","origin":"MIA","destination":"ORD","departureTime":"2018-03-24T10:15-04:00","arrivalTime":"2018-03-24T12:48-05:00","flightStatus":"On-Time","cost":"394"},{"flightNumber":"541","aircraftType":"321","origin":"MIA","destination":"ORD","departureTime":"2018-03-24T12:01-04:00","arrivalTime":"2018-03-24T14:30-05:00","flightStatus":"On-Time","cost":"367"},{"flightNumber":"1090","aircraftType":"32B","origin":"MIA","destination":"ORD","departureTime":"2018-03-24T13:50-04:00","arrivalTime":"2018-03-24T16:18-05:00","flightStatus":"On-Time","cost":"409"},{"flightNumber":"1284","aircraftType":"738","origin":"MIA","destination":"ORD","departureTime":"2018-03-24T16:05-04:00","arrivalTime":"2018-03-24T18:38-05:00","flightStatus":"On-Time","cost":"305"},{"flightNumber":"1109","aircraftType":"738","origin":"MIA","destination":"ORD","departureTime":"2018-03-24T16:55-04:00","arrivalTime":"2018-03-24T19:27-05:00","flightStatus":"On-Time","cost":"351"},{"flightNumber":"1448","aircraftType":"738","origin":"MIA","destination":"ORD","departureTime":"2018-03-24T18:05-04:00","arrivalTime":"2018-03-24T20:39-05:00","flightStatus":"On-Time","cost":"332"},{"flightNumber":"2394","aircraftType":"738","origin":"MIA","destination":"ORD","departureTime":"2018-03-24T18:30-04:00","arrivalTime":"2018-03-24T21:01-05:00","flightStatus":"On-Time","cost":"323"},{"flightNumber":"1612","aircraftType":"738","origin":"MIA","destination":"ORD","departureTime":"2018-03-24T19:35-04:00","arrivalTime":"2018-03-24T22:07-05:00","flightStatus":"On-Time","cost":"276"},{"flightNumber":"2521","aircraftType":"738","origin":"MIA","destination":"ORD","departureTime":"2018-03-24T21:30-04:00","arrivalTime":"2018-03-24T23:57-05:00","flightStatus":"On-Time","cost":"394"},{"flightNumber":"1202","aircraftType":"738","origin":"MIA","destination":"ORD","departureTime":"2018-03-24T11:11-04:00","arrivalTime":"2018-03-24T16:01-05:00","flightStatus":"On-Time","cost":"383"}]