[{"flightNumber":"8926","aircraftType":"77W","origin":"JFK","destination":"HKG","departureTime":"2018-03-31T10:00-04:00","arrivalTime":"2018-04-01T14:00+08:00","flightStatus":"On-Time","cost":"317"},{"flightNumber":"8927","aircraftType":"77W","origin":"JFK","destination":"HKG","departureTime":"2018-03-31T01:35-04:00","arrivalTime":"2018-04-01T05:15+08:00","flightStatus":"On-Time","cost":"348"},{"flightNumber":"8924","aircraftType":"77W","origin":"JFK","destination":"HKG","departureTime":"2018-03-31T14:55-04:00","arrivalTime":"2018-04-01T18:50+08:00","flightStatus":"On-Time","cost":"312"},{"flightNumber":"8942","aircraftType":"359","origin":"EWR","destination":"HKG","departureTime":"2018-03-31T01:45-04:00","arrivalTime":"2018-04-01T05:30+08:00","flightStatus":"On-Time","cost":"383"}]