[{"flightNumber":"2270","aircraftType":"738","origin":"JFK","destination":"ORD","departureTime":"2018-03-21T17:05-04:00","arrivalTime":"2018-03-21T19:08-05:00","flightStatus":"On-Time","cost":"361"},{"flightNumber":"2316","aircraftType":"738","origin":"EWR","destination":"ORD","departureTime":"2018-03-21T07:07-04:00","arrivalTime":"2018-03-21T08:55-05:00","flightStatus":"On-Time","cost":"290"},{"flightNumber":"304","aircraftType":"738","origin":"LGA","destination":"ORD","departureTime":"2018-03-21T06:30-04:00","arrivalTime":"2018-03-21T08:14-05:00","flightStatus":"On-Time","cost":"386"},{"flightNumber":"2587","aircraftType":"738","origin":"LGA","destination":"ORD","departureTime":"2018-03-21T07:30-04:00","arrivalTime":"2018-03-21T09:21-05:00","flightStatus":"On-Time","cost":"351"},{"flightNumber":"356","aircraftType":"32B","origin":"LGA","destination":"ORD","departureTime":"2018-03-21T08:30-04:00","arrivalTime":"2018-03-21T10:26-05:00","flightStatus":"On-Time","cost":"324"},{"flightNumber":"373","aircraftType":"738","origin":"LGA","destination":"ORD","departureTime":"2018-03-21T09:30-04:00","arrivalTime":"2018-03-21T11:26-05:00","flightStatus":"On-Time","cost":"329"},{"flightNumber":"2692","aircraftType":"738","origin":"EWR","destination":"ORD","departureTime":"2018-03-21T10:49-04:00","arrivalTime":"2018-03-21T12:30-05:00","flightStatus":"On-Time","cost":"402"},{"flightNumber":"328","aircraftType":"738","origin":"LGA","destination":"ORD","departureTime":"2018-03-21T10:30-04:00","arrivalTime":"2018-03-21T12:23-05:00","flightStatus":"On-Time","cost":"351"},{"flightNumber":"337","aircraftType":"738","origin":"LGA","destination":"ORD","departureTime":"2018-03-21T11:30-04:00","arrivalTime":"2018-03-21T13:23-05:00","flightStatus":"On-Time","cost":"349"},{"flightNumber":"390","aircraftType":"738","origin":"LGA","destination":"ORD","departureTime":"2018-03-21T12:30-04:00","arrivalTime":"2018-03-21T14:19-05:00","flightStatus":"On-Time","cost":"368"},{"flightNumber":"332","aircraftType":"738","origin":"LGA","destination":"ORD","departureTime":"2018-03-21T13:30-04:00","arrivalTime":"2018-03-21T15:12-05:00","flightStatus":"On-Time","cost":"319"},{"flightNumber":"3749","aircraftType":"CR7","origin":"EWR","destination":"ORD","departureTime":"2018-03-21T14:20-04:00","arrivalTime":"2018-03-21T15:53-05:00","flightStatus":"On-Time","cost":"371"},{"flightNumber":"303","aircraftType":"738","origin":"LGA","destination":"ORD","departureTime":"2018-03-21T14:30-04:00","arrivalTime":"2018-03-21T16:16-05:00","flightStatus":"On-Time","cost":"299"},{"flightNumber":"343","aircraftType":"738","origin":"LGA","destination":"ORD","departureTime":"2018-03-21T16:30-04:00","arrivalTime":"2018-03-21T18:22-05:00","flightStatus":"On-Time","cost":"356"},{"flightNumber":"345","aircraftType":"738","origin":"LGA","destination":"ORD","departureTime":"2018-03-21T17:30-04:00","arrivalTime":"2018-03-21T19:22-05:00","flightStatus":"On-Time","cost":"351"},{"flightNumber":"1598","aircraftType":"738","origin":"EWR","destination":"ORD","departureTime":"2018-03-21T17:30-04:00","arrivalTime":"2018-03-21T19:24-05:00","flightStatus":"On-Time","cost":"343"},{"flightNumber":"361","aircraftType":"738","origin":"LGA","destination":"ORD","departureTime":"2018-03-21T18:30-04:00","arrivalTime":"2018-03-21T20:21-05:00","flightStatus":"On-Time","cost":"386"},{"flightNumber":"3740","aircraftType":"E75","origin":"EWR","destination":"ORD","departureTime":"2018-03-21T19:05-04:00","arrivalTime":"2018-03-21T20:46-05:00","flightStatus":"On-Time","cost":"316"},{"flightNumber":"359","aircraftType":"738","origin":"LGA","destination":"ORD","departureTime":"2018-03-21T19:30-04:00","arrivalTime":"2018-03-21T21:18-05:00","flightStatus":"On-Time","cost":"330"},{"flightNumber":"371","aircraftType":"738","origin":"LGA","destination":"ORD","departureTime":"2018-03-21T20:30-04:00","arrivalTime":"2018-03-21T22:17-05:00","flightStatus":"On-Time","cost":"311"},{"flightNumber":"321","aircraftType":"738","origin":"LGA","destination":"ORD","departureTime":"2018-03-21T21:29-04:00","arrivalTime":"2018-03-21T23:17-05:00","flightStatus":"On-Time","cost":"347"}]