[{"flightNumber":"2332","aircraftType":"319","origin":"DFW","destination":"ORD","departureTime":"2018-03-17T07:00-05:00","arrivalTime":"2018-03-17T09:29-05:00","flightStatus":"On-Time","cost":"323"},{"flightNumber":"1499","aircraftType":"738","origin":"DFW","destination":"ORD","departureTime":"2018-03-17T08:00-05:00","arrivalTime":"2018-03-17T10:19-05:00","flightStatus":"On-Time","cost":"369"},{"flightNumber":"2761","aircraftType":"32B","origin":"DFW","destination":"ORD","departureTime":"2018-03-17T05:15-05:00","arrivalTime":"2018-03-17T07:38-05:00","flightStatus":"On-Time","cost":"360"},{"flightNumber":"1217","aircraftType":"32B","origin":"DFW","destination":"ORD","departureTime":"2018-03-17T09:00-05:00","arrivalTime":"2018-03-17T11:24-05:00","flightStatus":"On-Time","cost":"301"},{"flightNumber":"335","aircraftType":"32B","origin":"DFW","destination":"ORD","departureTime":"2018-03-17T10:30-05:00","arrivalTime":"2018-03-17T12:50-05:00","flightStatus":"On-Time","cost":"300"},{"flightNumber":"1258","aircraftType":"788","origin":"DFW","destination":"ORD","departureTime":"2018-03-17T11:45-05:00","arrivalTime":"2018-03-17T13:59-05:00","flightStatus":"On-Time","cost":"333"},{"flightNumber":"1233","aircraftType":"789","origin":"DFW","destination":"ORD","departureTime":"2018-03-17T12:35-05:00","arrivalTime":"2018-03-17T14:52-05:00","flightStatus":"On-Time","cost":"268"},{"flightNumber":"2535","aircraftType":"S80","origin":"DFW","destination":"ORD","departureTime":"2018-03-17T14:55-05:00","arrivalTime":"2018-03-17T17:19-05:00","flightStatus":"On-Time","cost":"348"},{"flightNumber":"2319","aircraftType":"S80","origin":"DFW","destination":"ORD","departureTime":"2018-03-17T16:17-05:00","arrivalTime":"2018-03-17T18:45-05:00","flightStatus":"On-Time","cost":"310"},{"flightNumber":"2467","aircraftType":"788","origin":"DFW","destination":"ORD","departureTime":"2018-03-17T18:35-05:00","arrivalTime":"2018-03-17T20:57-05:00","flightStatus":"On-Time","cost":"383"}]